rag/__init__.py
rag/cli/command.py
rag/cli/commands/__init__.py
rag/cli/commands/create.py
rag/cli/commands/dserve.py
rag/cli/commands/lint.py
rag/cli/commands/manage.py
rag/cli/commands/run.py
rag/cli/commands/serve.py
rag/cli/commands/settings.py
rag/cli/commands/shell.py
rag/cli/commands/test.py
rag/cli/commands/version.py
rag/cli/commands/worker.py
rag/cli/main.py
rag/cli/register.py
rag/core/application.py
rag/core/authorize.py
rag/core/errors.py
rag/core/json.py
rag/core/middleware/__init__.py
rag/core/middleware/rest.py
rag/core/middleware/token.py
rag/core/model.py
rag/core/models.py
rag/core/path.py
rag/core/patterns.py
rag/core/settings/__init__.py
rag/core/settings/default.py
rag/core/utils.py
rag/patches/__init__.py
rag/patches/channels.py
rag/patches/shell_plus.py
rag/signals/__init__.py
rag/signals/consumer.py
rag/signals/patterns.py
rag/signals/utils.py
rag/tasks/worker.py
rag/templates/.pylintrc
rag/templates/large/api/migrations/0001_initial.py
rag/templates/large/api/models/__init__.py
rag/templates/large/api/models/message.py
rag/templates/large/api/routes/messages.py
rag/templates/large/api/urls.py
rag/templates/large/app.py
rag/templates/large/poetry.toml
rag/templates/large/pyproject.toml
rag/templates/large/settings/__init__.py
rag/templates/large/settings/development.py
rag/templates/large/settings/production.py
rag/templates/large/settings/testing.py
rag/templates/large/static/index.html
rag/templates/large/tests/__init__.py
rag/templates/large/tests/models/test_message.py
rag/templates/large/tests/routes/test_messages.py
rag/templates/medium/api/controllers.py
rag/templates/medium/api/migrations/0001_initial.py
rag/templates/medium/api/migrations/__init__.py
rag/templates/medium/api/models.py
rag/templates/medium/api/settings.py
rag/templates/medium/api/urls.py
rag/templates/medium/app.py
rag/templates/medium/poetry.toml
rag/templates/medium/pyproject.toml
rag/templates/medium/tests/test_controllers.py
rag/templates/micro/api.py
rag-0.0.21.dist-info/WHEEL
rag-0.0.21.dist-info/METADATA
rag-0.0.21.dist-info/RECORD
