Metadata-Version: 2.1
Name: rag
Version: 0.0.21
Summary: 
Home-page: https://github.com/mraleson/rag.git
License: MIT
Author: Mark Raleson
Author-email: markraleson@outlook.com
Requires-Python: >=3.7,<4.0
Classifier: License :: OSI Approved :: MIT License
Classifier: Programming Language :: Python :: 3
Classifier: Programming Language :: Python :: 3.7
Classifier: Programming Language :: Python :: 3.8
Classifier: Programming Language :: Python :: 3.9
Requires-Dist: Django (>=3.1.5,<3.2.0)
Requires-Dist: celery (>=5.0.2,<5.1.0)
Requires-Dist: channels (>=3.0.2,<3.1.0)
Requires-Dist: channels-redis (>=3.2.0,<3.3.0)
Requires-Dist: daphne (>=3.0.1,<3.1.0)
Requires-Dist: django-extensions (>=3.0.9,<3.1.0)
Requires-Dist: ipython (>=7.19.0,<7.20.0)
Requires-Dist: pylint (>=2.7.2,<2.8.0)
Requires-Dist: pytest (>=6,<7)
Requires-Dist: pytest-django (>=4.1.0,<4.2.0)
Requires-Dist: pytest-mock (>=3.3.1,<3.4.0)
Requires-Dist: python-dateutil (>=2.8.1,<2.9.0)
Requires-Dist: ragclip (>=0.0.4,<0.1.0)
Requires-Dist: redis (>=3.5.3,<3.6.0)
Requires-Dist: watchdog (>=0.10.3,<0.11.0)
Project-URL: Repository, https://github.com/mraleson/rag.git
